Workbook

Sheet 口径说明
A1: 全国脑机接口企业投资地图—口径说明
A3: 核验日期 | B3: 46252
A4: 收录总数 | B4: =COUNTA(全国汇总!$B$2:$B$174) -> 173
A5: 地域口径 | B5: 按境内法律主体总部/主要注册地归属省级行政区；跨省研发中心不重复计数。
A6: 收录标准 | B6: 在核心脑机接口企业基础上，扩展收录具有明确产品或项目证据的脑电/脑功能监测、神经调控、神经康复、脑健康平台、关键器件、研发工具、临床转化和产业运营企业。纯概念炒作、仅采购设备且无研发/转化能力的医疗机构，以及无具体产品或项目披露的主体不纳入。
A7: 相关度 | B7: 核心企业=直接研发脑机接口；邻近应用=监测、调控、康复或脑健康产品与脑机接口存在明确技术连接；关键器件/平台=电极、芯片、脑磁/fNIRS、科研工具或数据平台；关联布局=上市公司或器械企业的实质研发/投资布局；临床转化/产业项目=以临床验证、区域运营或系统交付为主。
A8: 临床阶段 | B8: 按已获证/注册临床/科研临床/临床前/样机研发/消费级不适用分层；无稳定公开信息时明确写“未公开”，不做推断。
A9: 竞争力判断 | B9: 基于技术稀缺性、产品化、注册与临床、融资和产业资源的公开证据形成初步判断，不构成投资建议。
A10: 完整性边界 | B10: “全国”指对全部省级行政区做公开来源检索并在省份索引中呈现；不等同于工商数据库穷尽。早期企业可能因低曝光或信息滞后而遗漏，建议季度更新。
A12: 主要公开来源类型：政府/监管机构、大学/医院/实验室官网、企业官网、招股书/年报、主流财经媒体与行业研究报告。每条记录的URL见“公开来源”列。

Sheet 省份索引
A1: 省级行政区 | B1: 企业数量 | C1: 覆盖状态 | D1: 备注
A2: 北京市 | B2: =COUNTIF(全国汇总!$H$2:$H$173,A2) -> 20 | C2: =IF(B2=0,"暂未检索到符合口径对象","已收录") -> 已收录
A3: 天津市 | B3: =COUNTIF(全国汇总!$H$2:$H$173,A3) -> 7 | C3: =IF(B3=0,"暂未检索到符合口径对象","已收录") -> 已收录
A4: 河北省 | B4: =COUNTIF(全国汇总!$H$2:$H$173,A4) -> 1 | C4: =IF(B4=0,"暂未检索到符合口径对象","已收录") -> 已收录
A5: 山西省 | B5: =COUNTIF(全国汇总!$H$2:$H$173,A5) -> 0
A6: 内蒙古自治区 | B6: =COUNTIF(全国汇总!$H$2:$H$173,A6) -> 0
A7: 辽宁省 | B7: =COUNTIF(全国汇总!$H$2:$H$173,A7) -> 1 | C7: =IF(B7=0,"暂未检索到符合口径对象","已收录") -> 已收录
A8: 吉林省 | B8: =COUNTIF(全国汇总!$H$2:$H$173,A8) -> 0
A9: 黑龙江省 | B9: =COUNTIF(全国汇总!$H$2:$H$173,A9) -> 0
A10: 上海市 | B10: =COUNTIF(全国汇总!$H$2:$H$173,A10) -> 25 | C10: =IF(B10=0,"暂未检索到符合口径对象","已收录") -> 已收录
A11: 江苏省 | B11: =COUNTIF(全国汇总!$H$2:$H$173,A11) -> 32 | C11: =IF(B11=0,"暂未检索到符合口径对象","已收录") -> 已收录
A12: 浙江省 | B12: =COUNTIF(全国汇总!$H$2:$H$173,A12) -> 27 | C12: =IF(B12=0,"暂未检索到符合口径对象","已收录") -> 已收录
A13: 安徽省 | B13: =COUNTIF(全国汇总!$H$2:$H$173,A13) -> 3 | C13: =IF(B13=0,"暂未检索到符合口径对象","已收录") -> 已收录
A14: 福建省 | B14: =COUNTIF(全国汇总!$H$2:$H$173,A14) -> 2 | C14: =IF(B14=0,"暂未检索到符合口径对象","已收录") -> 已收录
A15: 江西省 | B15: =COUNTIF(全国汇总!$H$2:$H$173,A15) -> 3 | C15: =IF(B15=0,"暂未检索到符合口径对象","已收录") -> 已收录
A16: 山东省 | B16: =COUNTIF(全国汇总!$H$2:$H$173,A16) -> 4 | C16: =IF(B16=0,"暂未检索到符合口径对象","已收录") -> 已收录
A17: 河南省 | B17: =COUNTIF(全国汇总!$H$2:$H$173,A17) -> 2 | C17: =IF(B17=0,"暂未检索到符合口径对象","已收录") -> 已收录
A18: 湖北省 | B18: =COUNTIF(全国汇总!$H$2:$H$173,A18) -> 6 | C18: =IF(B18=0,"暂未检索到符合口径对象","已收录") -> 已收录
A19: 湖南省 | B19: =COUNTIF(全国汇总!$H$2:$H$173,A19) -> 1 | C19: =IF(B19=0,"暂未检索到符合口径对象","已收录") -> 已收录
A20: 广东省 | B20: =COUNTIF(全国汇总!$H$2:$H$173,A20) -> 20 | C20: =IF(B20=0,"暂未检索到符合口径对象","已收录") -> 已收录
A21: 广西壮族自治区 | B21: =COUNTIF(全国汇总!$H$2:$H$173,A21) -> 0
A22: 海南省 | B22: =COUNTIF(全国汇总!$H$2:$H$173,A22) -> 1 | C22: =IF(B22=0,"暂未检索到符合口径对象","已收录") -> 已收录
A23: 重庆市 | B23: =COUNTIF(全国汇总!$H$2:$H$173,A23) -> 2 | C23: =IF(B23=0,"暂未检索到符合口径对象","已收录") -> 已收录
A24: 四川省 | B24: =COUNTIF(全国汇总!$H$2:$H$173,A24) -> 11 | C24: =IF(B24=0,"暂未检索到符合口径对象","已收录") -> 已收录
A25: 贵州省 | B25: =COUNTIF(全国汇总!$H$2:$H$173,A25) -> 1 | C25: =IF(B25=0,"暂未检索到符合口径对象","已收录") -> 已收录
A26: 云南省 | B26: =COUNTIF(全国汇总!$H$2:$H$173,A26) -> 1 | C26: =IF(B26=0,"暂未检索到符合口径对象","已收录") -> 已收录
A27: 西藏自治区 | B27: =COUNTIF(全国汇总!$H$2:$H$173,A27) -> 0
A28: 陕西省 | B28: =COUNTIF(全国汇总!$H$2:$H$173,A28) -> 2 | C28: =IF(B28=0,"暂未检索到符合口径对象","已收录") -> 已收录
A29: 甘肃省 | B29: =COUNTIF(全国汇总!$H$2:$H$173,A29) -> 0
A30: 青海省 | B30: =COUNTIF(全国汇总!$H$2:$H$173,A30) -> 0
A31: 宁夏回族自治区 | B31: =COUNTIF(全国汇总!$H$2:$H$173,A31) -> 0
A32: 新疆维吾尔自治区 | B32: =COUNTIF(全国汇总!$H$2:$H$173,A32) -> 0
A33: 香港特别行政区 | B33: =COUNTIF(全国汇总!$H$2:$H$173,A33) -> 0
A34: 澳门特别行政区 | B34: =COUNTIF(全国汇总!$H$2:$H$173,A34) -> 0
A35: 台湾省 | B35: =COUNTIF(全国汇总!$H$2:$H$173,A35) -> 0

Sheet 全国汇总
A1: 序号 | B1: 公司名称 | C1: 技术路径 | D1: 产品介绍 | E1: 产品临床阶段 | F1: 融资情况 | G1: 竞争力判断 | H1: 所属省份 | I1: 总部城市 | J1: 相关度/类型 | K1: 公开来源 | L1: 核验日期
A2: 1 | B2: 北京诚益通控制工程科技股份有限公司 | C2: 非侵入式/侵入式布局 | D2: 经颅磁/导航、脑机接口康复样机及侵入式技术储备 | E2: 非侵入式样机与注册推进；侵入式处于储备/合作阶段 | F2: A股上市公司，以自有资金和子公司持续投入 | G2: 中高：康复渠道和制造基础较强，核心BCI产品仍需验证 | H2: 北京市 | I2: 北京 | J2: 关联布局 | K2: https://pdf.dfcfw.com/pdf/H301_AP202605101822122234_1.pdf | L2: 46252
A3: 2 | B3: 北京津发科技股份有限公司 | C3: 非侵入式/人因与生理信号 | D3: 脑电、眼动、生理信号采集和人因智能实验平台 | E3: 科研与工业用户规模化应用；医疗注册属性因产品而异 | F3: 融资情况未充分公开 | G3: 中：科研工具与客户基础扎实，可服务脑机接口研发验证；医疗端直接相关度较弱 | H3: 北京市 | I3: 北京 | J3: 关键器件/科研平台 | K3: https://www.sohu.com/a/1017268693_121277055 | L3: 46252
A4: 3 | B4: 北京决明科技有限公司 | C4: 认知脑机接口 | D4: 认知功能客观评估、靶向干预及个性化训练平台 | E4: 科研与场景验证阶段；注册信息未充分公开 | F4: 融资情况未充分公开 | G4: 中：认知评估闭环定位清晰，需持续核验医疗资质、临床数据与商业规模 | H4: 北京市 | I4: 北京 | J4: 邻近应用/脑健康平台 | K4: https://m.elecfans.com/article/7413259.html | L4: 46252
A5: 4 | B5: 北京脑连科技有限公司 | C5: 非侵入式/侵入式布局 | D5: 脑机接口医疗与智能硬件研发平台 | E5: 研发/样机阶段，注册信息未公开 | F5: 2024年获诚益通体系战略投资，金额未披露 | G5: 中：产业方协同明确，但独立产品与临床证据披露较少 | H5: 北京市 | I5: 北京 | J5: 核心企业 | K5: https://www.460.net.cn/news/show-359821.html | L5: 46252
A6: 5 | B6: 北京脑陆科技有限公司 | C6: 非侵入式 | D6: EEG采集硬件、脑电AI算法及情绪/认知/睡眠应用 | E6: 产品化与场景验证阶段；医疗注册信息未充分公开 | F6: 完成多轮股权融资，世纪华通等参与；金额未完整披露 | G6: 中高：专利与应用场景丰富，消费/医疗边界和规模化能力需持续观察 | H6: 北京市 | I6: 北京 | J6: 核心企业 | K6: https://zscqj.hubei.gov.cn/bmdt/ztzl/2023zt/zhlh2023/202601/t20260116_5857083.shtml https://pdf.dfcfw.com/pdf/H301_AP202605101822122234_1.pdf | L6: 46252
A7: 6 | B7: 北京宁矩科技有限公司（NeuraMatrix） | C7: 侵入式 | D7: 高通量神经信号采集芯片、植入式电极与无线脑机接口平台 | E7: 临床前/动物验证；人体注册进展未见稳定公开信息 | F7: A轮；华盖资本、经纬创投等参与，金额未公开 | G7: 中高：具备芯片—电极—系统全栈能力，侵入式平台稀缺；注册路径仍待验证 | H7: 北京市 | I7: 北京 | J7: 核心企业 | K7: https://www.ncsti.gov.cn/kjdt/ztbd/xydrgzn/lbt_848/202112/P020211231639066065610.pdf https://www.460.net.cn/news/show-359821.html | L7: 46252
A8: 7 | B8: 北京品驰医疗设备有限公司 | C8: 侵入式神经调控 | D8: DBS、VNS、SCS等植入式神经刺激系统及程控平台 | E8: 多款三类植入器械已商业化；脑机接口融合处于拓展阶段 | F8: 多轮融资后实现产业化，具体最新轮次未披露 | G8: 中高：植入器械注册、制造与医院渠道优势突出；BCI读取能力仍在延展 | H8: 北京市 | I8: 北京 | J8: 关联布局 | K8: https://wap.miit.gov.cn/cms_files/filemanager/1226211233/attach/20256/65ade62451fe4eb09e40e5576208b989.docx https://pdf.dfcfw.com/pdf/H301_AP202605101822122234_1.pdf | L8: 46252
A9: 8 | B9: 北京儒奥医疗科技有限公司 | C9: 非侵入式/经颅超声 | D9: 头戴式经颅超声治疗头、经颅超声神经调控机器人和神经康复方案 | E9: 经颅超声产品已有注册与医院应用；机器人项目处于创新任务阶段 | F9: 融资情况未充分公开 | G9: 中高：无创深部神经调控方向差异化，注册基础较好；闭环脑机能力仍需临床验证 | H9: 北京市 | I9: 北京 | J9: 邻近应用/神经调控 | K9: https://xxcx.yjj.beijing.gov.cn/eportal/ui?pageId=723864 https://kcycrawlerfile.oss-cn-beijing.aliyuncs.com/2026/01/12/900eeb7687194399bf85a452ae3d180c.pdf | L9: 46252
A10: 9 | B10: 北京神舞科技有限公司（NeuroDance） | C10: 非侵入式 | D10: ND系列脑电采集系统、睡眠监测、脑控无人机与认知训练产品 | E10: ND系列已获二类医疗器械资质；消费级产品已销售 | F10: 2026年A轮数千万元；更早轮次未完整披露 | G10: 中高：清华团队、医疗资质和实时远程脑电产品形成差异化 | H10: 北京市 | I10: 北京 | J10: 核心企业 | K10: https://www.neurodance.cn/ | L10: 46252
A11: 10 | B11: 北京芯智达神经技术有限公司 | C11: 半侵入式/侵入式 | D11: “北脑一号/北脑二号”柔性高通量无线全植入脑机系统 | E11: 已启动注册临床试验 | F11: 北京市财政与中关村发展集团出资设立，首期注册资本1亿元 | G11: 高：政府牵引、医研协同和注册临床进度领先 | H11: 北京市 | I11: 北京 | J11: 核心企业 | K11: https://paper.people.com.cn/rmrb/pc/attachement/202604/14/7cc56cec-11a5-491b-97d2-a98ba8423cad.pdf https://www.460.net.cn/news/show-359821.html | L11: 46252
A12: 11 | B12: 北京银河方圆科技有限公司 | C12: 非侵入式/精准神经调控 | D12: 脑环路起搏器、可视化导航经颅磁刺激及阿尔茨海默病经颅刺激系统 | E12: 已取得医疗器械生产许可；相关项目入选国家创新任务 | F12: 融资情况未充分公开 | G12: 中高：脑科学园区与临床资源协同强，已形成明确的检测—导航—调控路径 | H12: 北京市 | I12: 北京 | J12: 邻近应用/神经调控 | K12: https://invest.beijing.gov.cn/zwgk/sqgzdt/202606/t20260626_4726234.html https://kcycrawlerfile.oss-cn-beijing.aliyuncs.com/2026/01/12/900eeb7687194399bf85a452ae3d180c.pdf | L12: 46252
A13: 12 | B13: 北京优脑银河科技有限公司 | C13: 非侵入式/精准神经调控 | D13: 个体化脑功能图谱、脑网络检测与精准调控平台 | E13: 科研与临床合作阶段；部分产品处于注册/验证过程中 | F13: 已完成多轮融资，公开金额不完整 | G13: 中高：脑功能图谱技术有壁垒，商业化依赖临床证据与适应证拓展 | H13: 北京市 | I13: 北京 | J13: 核心企业 | K13: https://pdf.dfcfw.com/pdf/H3_AP202503041644026495_1.pdf https://www.460.net.cn/news/show-359821.html | L13: 46252
... A173: 172 | B173: 西安臻泰智能科技有限公司 | C173: 非侵入式/康复机器人 | D173: 脑机接口智能康复机器人及整体解决方案 | E173: 产品已在多家医院应用，推进三类器械申报 | F173: 天使轮和A轮；联想创投、胡杨林资本、奇绩创坛等参与 | G173: 中高：康复落地较早，需持续核验获证与规模收入 | H173: 陕西省 | I173: 西安 | J173: 核心企业 | K173: https://www.460.net.cn/news/show-359821.html | L173: 46252
B174: 上海全澜科技有限公司 | C174: ‌非侵入性神经调控 | D174: 脑机接口输入采集设备供应商（集成芯片及系统，不含电极） | E174: 科研产品和服务已规模化应用 | F174: 天使轮和pre-A轮：中科创星、华大松禾天使基金 | G174: 中高：全澜科技依托较强的脑科学团队和“脑电检测—个体靶点—闭环刺激”差异化技术具备一定先发优势，但核心治疗产品尚未获证、临床与商业化验证不足，现阶段竞争力中等偏强。 | H174: 上海市 | I174: 上海市 | J174: 核心企业 | K174: https://www.eegion.com/ | L174: 46252

Sheet 北京市
A1: 序号 | B1: 公司名称 | C1: 技术路径 | D1: 产品介绍 | E1: 产品临床阶段 | F1: 融资情况 | G1: 竞争力判断 | H1: 所属省份 | I1: 总部城市 | J1: 相关度/类型 | K1: 公开来源 | L1: 核验日期
A2: 1 | B2: 北京诚益通控制工程科技股份有限公司 | C2: 非侵入式/侵入式布局 | D2: 经颅磁/导航、脑机接口康复样机及侵入式技术储备 | E2: 非侵入式样机与注册推进；侵入式处于储备/合作阶段 | F2: A股上市公司，以自有资金和子公司持续投入 | G2: 中高：康复渠道和制造基础较强，核心BCI产品仍需验证 | H2: 北京市 | I2: 北京 | J2: 关联布局 | K2: https://pdf.dfcfw.com/pdf/H301_AP202605101822122234_1.pdf | L2: 46252
A3: 2 | B3: 北京津发科技股份有限公司 | C3: 非侵入式/人因与生理信号 | D3: 脑电、眼动、生理信号采集和人因智能实验平台 | E3: 科研与工业用户规模化应用；医疗注册属性因产品而异 | F3: 融资情况未充分公开 | G3: 中：科研工具与客户基础扎实，可服务脑机接口研发验证；医疗端直接相关度较弱 | H3: 北京市 | I3: 北京 | J3: 关键器件/科研平台 | K3: https://www.sohu.com/a/1017268693_121277055 | L3: 46252
A4: 3 | B4: 北京决明科技有限公司 | C4: 认知脑机接口 | D4: 认知功能客观评估、靶向干预及个性化训练平台 | E4: 科研与场景验证阶段；注册信息未充分公开 | F4: 融资情况未充分公开 | G4: 中：认知评估闭环定位清晰，需持续核验医疗资质、临床数据与商业规模 | H4: 北京市 | I4: 北京 | J4: 邻近应用/脑健康平台 | K4: https://m.elecfans.com/article/7413259.html | L4: 46252
A5: 4 | B5: 北京脑连科技有限公司 | C5: 非侵入式/侵入式布局 | D5: 脑机接口医疗与智能硬件研发平台 | E5: 研发/样机阶段，注册信息未公开 | F5: 2024年获诚益通体系战略投资，金额未披露 | G5: 中：产业方协同明确，但独立产品与临床证据披露较少 | H5: 北京市 | I5: 北京 | J5: 核心企业 | K5: https://www.460.net.cn/news/show-359821.html | L5: 46252
A6: 5 | B6: 北京脑陆科技有限公司 | C6: 非侵入式 | D6: EEG采集硬件、脑电AI算法及情绪/认知/睡眠应用 | E6: 产品化与场景验证阶段；医疗注册信息未充分公开 | F6: 完成多轮股权融资，世纪华通等参与；金额未完整披露 | G6: 中高：专利与应用场景丰富，消费/医疗边界和规模化能力需持续观察 | H6: 北京市 | I6: 北京 | J6: 核心企业 | K6: https://zscqj.hubei.gov.cn/bmdt/ztzl/2023zt/zhlh2023/202601/t20260116_5857083.shtml https://pdf.dfcfw.com/pdf/H301_AP202605101822122234_1.pdf | L6: 46252
A7: 6 | B7: 北京宁矩科技有限公司（NeuraMatrix） | C7: 侵入式 | D7: 高通量神经信号采集芯片、植入式电极与无线脑机接口平台 | E7: 临床前/动物验证；人体注册进展未见稳定公开信息 | F7: A轮；华盖资本、经纬创投等参与，金额未公开 | G7: 中高：具备芯片—电极—系统全栈能力，侵入式平台稀缺；注册路径仍待验证 | H7: 北京市 | I7: 北京 | J7: 核心企业 | K7: https://www.ncsti.gov.cn/kjdt/ztbd/xydrgzn/lbt_848/202112/P020211231639066065610.pdf https://www.460.net.cn/news/show-359821.html | L7: 46252
A8: 7 | B8: 北京品驰医疗设备有限公司 | C8: 侵入式神经调控 | D8: DBS、VNS、SCS等植入式神经刺激系统及程控平台 | E8: 多款三类植入器械已商业化；脑机接口融合处于拓展阶段 | F8: 多轮融资后实现产业化，具体最新轮次未披露 | G8: 中高：植入器械注册、制造与医院渠道优势突出；BCI读取能力仍在延展 | H8: 北京市 | I8: 北京 | J8: 关联布局 | K8: https://wap.miit.gov.cn/cms_files/filemanager/1226211233/attach/20256/65ade62451fe4eb09e40e5576208b989.docx https://pdf.dfcfw.com/pdf/H301_AP202605101822122234_1.pdf | L8: 46252
A9: 8 | B9: 北京儒奥医疗科技有限公司 | C9: 非侵入式/经颅超声 | D9: 头戴式经颅超声治疗头、经颅超声神经调控机器人和神经康复方案 | E9: 经颅超声产品已有注册与医院应用；机器人项目处于创新任务阶段 | F9: 融资情况未充分公开 | G9: 中高：无创深部神经调控方向差异化，注册基础较好；闭环脑机能力仍需临床验证 | H9: 北京市 | I9: 北京 | J9: 邻近应用/神经调控 | K9: https://xxcx.yjj.beijing.gov.cn/eportal/ui?pageId=723864 https://kcycrawlerfile.oss-cn-beijing.aliyuncs.com/2026/01/12/900eeb7687194399bf85a452ae3d180c.pdf | L9: 46252
A10: 9 | B10: 北京神舞科技有限公司（NeuroDance） | C10: 非侵入式 | D10: ND系列脑电采集系统、睡眠监测、脑控无人机与认知训练产品 | E10: ND系列已获二类医疗器械资质；消费级产品已销售 | F10: 2026年A轮数千万元；更早轮次未完整披露 | G10: 中高：清华团队、医疗资质和实时远程脑电产品形成差异化 | H10: 北京市 | I10: 北京 | J10: 核心企业 | K10: https://www.neurodance.cn/ | L10: 46252
A11: 10 | B11: 北京芯智达神经技术有限公司 | C11: 半侵入式/侵入式 | D11: “北脑一号/北脑二号”柔性高通量无线全植入脑机系统 | E11: 已启动注册临床试验 | F11: 北京市财政与中关村发展集团出资设立，首期注册资本1亿元 | G11: 高：政府牵引、医研协同和注册临床进度领先 | H11: 北京市 | I11: 北京 | J11: 核心企业 | K11: https://paper.people.com.cn/rmrb/pc/attachement/202604/14/7cc56cec-11a5-491b-97d2-a98ba8423cad.pdf https://www.460.net.cn/news/show-359821.html | L11: 46252
A12: 11 | B12: 北京银河方圆科技有限公司 | C12: 非侵入式/精准神经调控 | D12: 脑环路起搏器、可视化导航经颅磁刺激及阿尔茨海默病经颅刺激系统 | E12: 已取得医疗器械生产许可；相关项目入选国家创新任务 | F12: 融资情况未充分公开 | G12: 中高：脑科学园区与临床资源协同强，已形成明确的检测—导航—调控路径 | H12: 北京市 | I12: 北京 | J12: 邻近应用/神经调控 | K12: https://invest.beijing.gov.cn/zwgk/sqgzdt/202606/t20260626_4726234.html https://kcycrawlerfile.oss-cn-beijing.aliyuncs.com/2026/01/12/900eeb7687194399bf85a452ae3d180c.pdf | L12: 46252
A13: 12 | B13: 北京优脑银河科技有限公司 | C13: 非侵入式/精准神经调控 | D13: 个体化脑功能图谱、脑网络检测与精准调控平台 | E13: 科研与临床合作阶段；部分产品处于注册/验证过程中 | F13: 已完成多轮融资，公开金额不完整 | G13: 中高：脑功能图谱技术有壁垒，商业化依赖临床证据与适应证拓展 | H13: 北京市 | I13: 北京 | J13: 核心企业 | K13: https://pdf.dfcfw.com/pdf/H3_AP202503041644026495_1.pdf https://www.460.net.cn/news/show-359821.html | L13: 46252
... A21: 20 | B21: 中科知影（北京）科技有限公司 | C21: 非侵入式脑磁接口 | D21: 原子磁力计脑磁图系统及脑磁数据分析服务 | E21: 科研/临床研究设备阶段 | F21: A轮；英诺、金科君创、国泰创投等参与，金额未公开 | G21: 中高：OPM脑磁图属于稀缺上游平台，具备科研向临床转化潜力 | H21: 北京市 | I21: 北京 | J21: 关键器件/平台 | K21: https://www.460.net.cn/news/show-359821.html | L21: 46252

Sheet 天津市
A1: 序号 | B1: 公司名称 | C1: 技术路径 | D1: 产品介绍 | E1: 产品临床阶段 | F1: 融资情况 | G1: 竞争力判断 | H1: 所属省份 | I1: 总部城市 | J1: 相关度/类型 | K1: 公开来源 | L1: 核验日期
A2: 1 | B2: 大天医学工程（天津）有限公司 | C2: 非侵入式/脑机康复 | D2: 脑—机—肌信息环路助行机器人和神经康复系统 | E2: 科研成果转化与产品化阶段 | F2: 融资情况未充分公开 | G2: 中：天津大学医工协同基础较强，产品注册与规模化客户信息待补充 | H2: 天津市 | I2: 天津 | J2: 邻近应用/康复设备 | K2: https://zscqj.hubei.gov.cn/bmdt/ztzl/2023zt/zhlh2023/202601/t20260116_5857083.shtml | L2: 46252
A3: 2 | B3: 神工谛听（天津）科技有限公司 | C3: 非侵入式/采集与刺激 | D3: 低噪声脑电采集、高密度电刺激、群体脑机接口和教学系统 | E3: 已向多所高校、医院交付平台项目 | F3: 融资情况未公开 | G3: 中高：天津大学脑机生态协同明显，科研市场已有交付；医疗注册尚待推进 | H3: 天津市 | I3: 天津 | J3: 核心企业/科研平台 | K3: https://www.sohu.com/a/1017268693_121277055 | L3: 46252
A4: 3 | B4: 燧世（天津）智能科技有限公司 | C4: 非侵入式 | D4: “神工”系列脑电采集、听觉评估、抑郁评估与康复设备 | E4: 部分产品已获二类医疗器械证，持续临床应用 | F4: 天开园孵化，融资情况未充分公开 | G4: 中高：天津大学成果转化与医疗注册基础较好 | H4: 天津市 | I4: 天津 | J4: 核心企业 | K4: https://kxjs.tj.gov.cn/ZWGK4143/ZXGZ7816/sysgz/gzdtsys/202505/t20250523_6937987.html | L4: 46252
A5: 4 | B5: 天津明视脑机科技有限公司 | C5: 视觉脑机接口 | D5: 视觉重建与消费级脑机接口产品 | E5: 研发/临床前阶段 | F5: 2026年天使轮系列累计约1.5亿元 | G5: 中高：资金与视觉重建方向突出，仍需技术和临床验证 | H5: 天津市 | I5: 天津 | J5: 核心企业 | K5: https://www.460.net.cn/news/show-359821.html | L5: 46252
A6: 5 | B6: 天津脑机接口产业集团有限公司 | C6: 产业平台/多路线 | D6: 脑机接口成果转化、产业投资与子公司孵化平台 | E6: 平台建设与项目落地阶段 | F6: 2026年由海河实验室、天大科技园、泰达控股等战略出资，注册资本10亿元 | G6: 高：国资、实验室与产业平台一体化，需观察子公司产品兑现 | H6: 天津市 | I6: 天津 | J6: 产业平台 | K6: https://www.460.net.cn/news/show-359821.html | L6: 46252
A7: 6 | B7: 天津一行与航科技有限公司 | C7: 侵入式芯片 | D7: 刺激、同步/异步采集和高通量数据传输脑机芯片及IP定制 | E7: 多款芯片已完成硅基验证，提供定制和授权服务 | F7: 融资情况未充分公开 | G7: 中高：专用芯片矩阵完整，量产良率、客户验证和收入规模是关键 | H7: 天津市 | I7: 天津 | J7: 关键器件/平台 | K7: https://www.sohu.com/a/1017268693_121277055 | L7: 46252
A8: 7 | B8: 中电云脑（天津）科技有限公司 | C8: 非侵入式/芯片 | D8: “脑语者”编解码芯片、脑电采集芯片、脑机接口软件与神工系列产品 | E8: 部分二类医疗器械已获证并应用 | F8: 2024年A轮，金额未披露 | G8: 高：央企平台、自主芯片与产品体系完整，临床规模化能力较强 | H8: 天津市 | I8: 天津 | J8: 核心企业 | K8: https://www.cecbrain.com/ | L8: 46252

Sheet 河北省
A1: 序号 | B1: 公司名称 | C1: 技术路径 | D1: 产品介绍 | E1: 产品临床阶段 | F1: 融资情况 | G1: 竞争力判断 | H1: 所属省份 | I1: 总部城市 | J1: 相关度/类型 | K1: 公开来源 | L1: 核验日期
A2: 1 | B2: 河北格美医疗器械科技有限公司 | C2: 非侵入式/脑电治疗 | D2: 脑电治疗仪及康复理疗设备 | E2: 产品已商业化；与实时解码闭环脑机接口的直接程度有限 | F2: 融资情况未公开 | G2: 观察：属于中科搏锐式脑部诊疗设备邻近企业，需核验脑电采集、解码和闭环能力 | H2: 河北省 | I2: 石家庄 | J2: 邻近应用/临床设备 | K2: https://gmkf.cn/ | L2: 46252

Sheet 辽宁省
A1: 序号 | B1: 公司名称 | C1: 技术路径 | D1: 产品介绍 | E1: 产品临床阶段 | F1: 融资情况 | G1: 竞争力判断 | H1: 所属省份 | I1: 总部城市 | J1: 相关度/类型 | K1: 公开来源 | L1: 核验日期
A2: 1 | B2: 辽宁舜脑智能科技有限公司 | C2: 非侵入式/康复系统集成 | D2: 脑机接口康复训练、手功能康复和脑机外骨骼项目建设及系统交付 | E2: 已中标大连医院脑机接口设备项目；部分设备由合作厂商供货 | F2: 融资情况未公开 | G2: 观察：具备项目落地和渠道能力，但核心产品自主性需与山东海天等供应商拆分核验 | H2: 辽宁省 | I2: 大连 | J2: 产业项目/渠道 | K2: https://www.ccgp.gov.cn/cggg/dfgg/zbgg/202512/t20251223_25973430.htm | L2: 46252

Sheet 上海市
A1: 序号 | B1: 公司名称 | C1: 技术路径 | D1: 产品介绍 | E1: 产品临床阶段 | F1: 融资情况 | G1: 竞争力判断 | H1: 所属省份 | I1: 总部城市 | J1: 相关度/类型 | K1: 公开来源 | L1: 核验日期
A2: 1 | B2: 国科欣脑（上海）智能科技有限公司 | C2: 非侵入式/消费与科研 | D2: 多模态脑机接口工作站、脑机接口耳机、脑电采集模组及助听器方案 | E2: 2025年成立，处于原型研发与早期产品化阶段 | F2: 融资情况未公开 | G2: 观察：产品矩阵覆盖采集模组到终端，但成立时间短、医疗资质和客户验证有限 | H2: 上海市 | I2: 上海 | J2: 邻近应用/早期企业 | K2: https://www.gkxn.com.cn/ | L2: 46252
A3: 2 | B3: 锦脑医疗科技（上海）有限公司 | C3: 侵入式/神经调控 | D3: 植入式脑机接口与神经调控临床产品 | E3: 研发/临床前阶段 | F3: 2026年完成数千万元天使轮 | G3: 中：临床产品方向明确，处于早期，需要观察注册与动物/人体数据 | H3: 上海市 | I3: 上海 | J3: 核心企业 | K3: https://www.jnmedtech.com/ | L3: 46252
A4: 3 | B4: 聚芯医疗科技（上海）有限公司 | C4: 侵入式/医疗器械 | D4: 脑机接口与神经调控医疗器械平台 | E4: 研发/临床转化阶段 | F4: 2026年完成近2亿元C轮 | G4: 中高：资本认可度高，公开产品与临床细节有待补充 | H4: 上海市 | I4: 上海 | J4: 核心企业 | K4: https://www.460.net.cn/news/show-359821.html | L4: 46252
A5: 4 | B5: 上海傲意信息科技有限公司 | C5: 非侵入式神经接口/肌电接口 | D5: 智能仿生手、外骨骼、神经肌电控制平台 | E5: 产品已商业化并进入康复与消费场景 | F5: 2026年完成约1.5亿元C轮，中金脑科学基金领投 | G5: 中高：商业化和量产能力较强，但严格意义BCI占比需区分 | H5: 上海市 | I5: 上海 | J5: 核心企业 | K5: https://www.460.net.cn/news/show-359821.html | L5: 46252
A6: 5 | B6: 上海帝仪科技有限公司 | C6: 非侵入式/脑电监测 | D6: 高性能脑电采集、睡眠与脑功能评估系统 | E6: 研发与科研/医疗场景验证阶段 | F6: 融资情况未充分公开 | G6: 中：标准化参与度高，需补充获证产品与商业化数据 | H6: 上海市 | I6: 上海 | J6: 核心企业 | K6: https://wap.miit.gov.cn/cms_files/filemanager/1226211233/attach/20256/65ade62451fe4eb09e40e5576208b989.docx | L6: 46252
A7: 6 | B7: 上海东脑智合技术有限公司 | C7: 侵入式 | D7: 侵入式脑机接口全栈系统与医疗可穿戴产品 | E7: 研发/临床前阶段 | F7: 2026年A轮，金额未披露 | G7: 中：全栈定位清晰，公开技术和临床数据有限 | H7: 上海市 | I7: 上海 | J7: 核心企业 | K7: https://www.460.net.cn/news/show-359821.html | L7: 46252
A8: 7 | B8: 上海复通汇智医疗科技有限公司 | C8: 超声脑机接口 | D8: tFUS-Mind超声脑机接口与神经调控设备 | E8: 原型/临床前研究阶段 | F8: 2026年天使轮，金额未披露 | G8: 中高：超声路径具前沿性，需验证安全性、分辨率和临床适应证 | H8: 上海市 | I8: 上海 | J8: 核心企业 | K8: https://www.460.net.cn/news/show-359821.html | L8: 46252
A9: 8 | B9: 上海海每康智能医疗科技有限公司 | C9: 非侵入式/外骨骼 | D9: 基于脑可塑模型的柔性控制外骨骼与康复系统 | E9: 样机与场景验证阶段 | F9: 2024年近千万元天使轮，汉理资本投资 | G9: 中：脑机+外骨骼场景明确，医院验证和注册进度待观察 | H9: 上海市 | I9: 上海 | J9: 核心企业 | K9: https://www.460.net.cn/news/show-359821.html | L9: 46252
A10: 9 | B10: 上海阶梯医疗科技有限公司 | C10: 侵入式 | D10: 超柔性微纳电极、全植入无线脑机接口系统与手术配套 | E10: 进入创新器械绿色通道并推进多中心注册临床 | F10: 2026年完成约5亿元战略融资；近一年累计融资超过11亿元 | G10: 高：柔性电极、植入系统、资本与临床进度均处国内前列 | H10: 上海市 | I10: 上海 | J10: 核心企业 | K10: https://www.460.net.cn/news/show-359821.html https://pdf.dfcfw.com/pdf/H301_AP202605101822122234_1.pdf | L10: 46252
A11: 10 | B11: 上海锦徕信息科技有限公司 | C11: 脑机数据平台 | D11: 脑科学数据协同、脑疾病数据管理、脑机数据融合分析与医学影像科研平台 | E11: 已在50余家产学研医客户部署 | F11: 融资情况未充分公开 | G11: 中：脑机数据基础设施定位明确，竞争力取决于医院数据壁垒和算法生态 | H11: 上海市 | I11: 上海 | J11: 关键器件/数据平台 | K11: https://www.sohu.com/a/1017268693_121277055 | L11: 46252
A12: 11 | B12: 上海空山慈科技有限公司 | C12: 非侵入式神经调控 | D12: 脑信号解析与超声/磁/电/光多模态调控平台 | E12: 临床前/概念验证阶段 | F12: 2026年Pre-A轮，云启资本领投，金额未披露 | G12: 中高：多模态神经调控平台有潜力，仍处早期验证 | H12: 上海市 | I12: 上海 | J12: 核心企业 | K12: https://www.460.net.cn/news/show-359821.html | L12: 46252
A13: 12 | B13: 上海零唯一思科技有限公司 | C13: 情感脑机接口 | D13: 情绪评估、抑郁筛查与脑电大模型平台 | E13: 科研成果与标准验证阶段；医疗注册信息未充分公开 | F13: 融资情况未充分公开 | G13: 中高：情感BCI和脑电大模型定位鲜明，商业化证据仍需积累 | H13: 上海市 | I13: 上海 | J13: 核心企业 | K13: https://sdodt.com/index.php?c=show&id=57&s=xinwen | L13: 46252
... A26: 25 | B26: 心语未来（上海）医疗科技有限公司 | C26: 非侵入式/神经解码 | D26: 下一代非侵入式脑机系统、神经信号解码及意图识别平台 | E26: 早期研发与合作验证阶段 | F26: 融资情况未充分公开 | G26: 观察：已进入上海脑机产业集聚区并开展前沿计算合作，产品临床进展待披露 | H26: 上海市 | I26: 上海 | J26: 邻近应用/早期企业 | K26: https://www.shanghai.gov.cn/nw15343/20250714/38d480e4573a49778830ea605991e599.html https://finance.sina.com.cn/jjxw/2026-07-23/doc-iniiusky8286446.shtml | L26: 46252
B27: 上海全澜科技有限公司 | C27: ‌非侵入性神经调控 | D27: 脑机接口输入采集设备供应商（集成芯片及系统，不含电极） | E27: 科研产品和服务已规模化应用 | F27: 天使轮和pre-A轮：中科创星、华大松禾天使基金 | G27: 中高：全澜科技依托较强的脑科学团队和“脑电检测—个体靶点—闭环刺激”差异化技术具备一定先发优势，但核心治疗产品尚未获证、临床与商业化验证不足，现阶段竞争力中等偏强。 | H27: 上海市 | I27: 上海市 | J27: 核心企业 | K27: https://www.eegion.com/ | L27: 46252

Sheet 江苏省
A1: 序号 | B1: 公司名称 | C1: 技术路径 | D1: 产品介绍 | E1: 产品临床阶段 | F1: 融资情况 | G1: 竞争力判断 | H1: 所属省份 | I1: 总部城市 | J1: 相关度/类型 | K1: 公开来源 | L1: 核验日期
A2: 1 | B2: 博睿康科技（常州）股份有限公司（Neuracle） | C2: 非侵入式/半侵入式 | D2: 科研级脑电、医疗级脑电与NEO微创植入式脑机接口系统 | E2: NEO获三类医疗器械注册证并进入临床应用；多条产品线已商业化 | F2: E轮及以后；2026年科创板IPO获受理，拟募资25亿元 | G2: 高：采集设备现金流、植入式获证与IPO进展构成综合领先优势 | H2: 江苏省 | I2: 常州 | J2: 核心企业 | K2: https://qxb-pdf-osscache.qixin.com/AnBaseinfo/38576b8f5a72cec662cce82d85be813f.pdf https://pdf.dfcfw.com/pdf/H301_AP202605101822122234_1.pdf | L2: 46252
A3: 2 | B3: 常州航脑科技有限公司 | C3: 非侵入式/可穿戴 | D3: 脑机接口医疗器械与可穿戴设备 | E3: 研发/样机阶段 | F3: 2026年获战略投资，金额未披露 | G3: 观察：处于早期，需核验产品指标、客户与注册计划 | H3: 江苏省 | I3: 常州 | J3: 核心企业 | K3: https://www.460.net.cn/news/show-359821.html | L3: 46252
A4: 3 | B4: 常州瑞神安医疗器械有限公司 | C4: 侵入式/植入神经调控 | D4: DBS、SCS、VNS、SEEG颅内电极及耳甲迷走神经刺激产品 | E4: 多款Ⅲ类产品已获批；CNS脑深部刺激系统2025年获批 | F4: 已完成多轮融资，爱朋医疗、荣安创投等参与 | G4: 高：植入器械注册和全产品线优势突出，是双向脑机/闭环调控的重要邻近平台 | H4: 江苏省 | I4: 常州 | J4: 邻近应用/植入调控 | K4: https://www.rishena.com/ | L4: 46252
A5: 4 | B5: 常州弈脑科技有限公司 | C5: 脑机接口/神经调控 | D5: 脑机接口与神经调控产品（公开细节有限） | E5: 研发/临床转化阶段 | F5: 融资情况未公开 | G5: 观察：入选省级产融路演，公开信息较少 | H5: 江苏省 | I5: 常州 | J5: 核心企业 | K5: https://www.jiangsu.gov.cn/art/2026/5/28/art_60095_11777182.html | L5: 46252
A6: 5 | B6: 丹阳慧创医疗设备有限公司 | C6: 非侵入式/fNIRS | D6: 近红外脑功能成像与脑功能监测系统 | E6: 多款设备已商业化并进入医院/科研机构 | F6: 融资情况未充分公开 | G6: 中高：fNIRS国产化和临床渠道较成熟，严格BCI交互能力需区分 | H6: 江苏省 | I6: 丹阳 | J6: 关键器件/平台 | K6: https://www.tjh.com.cn/api/preview/1/125/55927 | L6: 46252
A7: 6 | B7: 江苏阿德智能科技有限公司 | C7: 非侵入式 | D7: 远程脑机大脑健康检测与数字化闭环干预产品 | E7: 产品化/场景验证阶段 | F7: 融资情况未充分公开 | G7: 中：远程脑健康场景明确，医学证据与合规边界需关注 | H7: 江苏省 | I7: 南京 | J7: 核心企业 | K7: https://www.nanjing.gov.cn/xxgkn/jytabljggk/2025njytabl/shizxta/202512/t20251203_5704650.html | L7: 46252
A8: 7 | B8: 江苏爱朋医疗科技股份有限公司 | C8: 植入式/非侵入式投资布局 | D8: 参股瑞神安、设立脑机接口基金并通过朋睿脑科学开展脑电与麻醉监护研究 | E8: 瑞神安多款植入产品已获证；自身脑机产品处于布局阶段 | F8: 创业板上市公司，以产业投资和控股子公司方式投入 | G8: 中：资本与临床渠道协同明显，自研脑机核心技术占比需进一步核验 | H8: 江苏省 | I8: 南通 | J8: 关联布局 | K8: https://file.finance.sina.com.cn/cn/diaoyan/jgdy/2026/2026-03/2026-03-09/10175735_1.PDF | L8: 46252
A9: 8 | B9: 江苏德长医疗科技有限公司 | C9: 非侵入式/脑肌电与动作捕捉 | D9: 无线表面肌电/脑电系统、动作捕捉、步态分析和智能助行平台 | E9: 科研与康复产品已商业化 | F9: 融资情况未充分公开 | G9: 中：多模态运动—脑肌电工具适合脑机康复研发，医疗级闭环产品仍需核验 | H9: 江苏省 | I9: 常熟 | J9: 关键器件/科研平台 | K9: https://www.sohu.com/a/1017268693_121277055 | L9: 46252
A10: 9 | B10: 江苏东健脑际医疗技术有限公司 | C10: 非侵入式/工业安全 | D10: 多模态脑电解析与工业人员疲劳、注意力风险监测系统 | E10: 工业场景验证与产品化阶段 | F10: 融资情况未公开 | G10: 中：将医疗级脑电用于工业安全，场景差异化明显；规模化订单与误报控制待验证 | H10: 江苏省 | I10: 南京 | J10: 邻近应用/工业脑机 | K10: https://www.sohu.com/a/1017268693_121277055 | L10: 46252
A11: 10 | B11: 江苏集萃脑科技股份有限公司 | C11: 非侵入式/类脑平台 | D11: 脑机接口与类脑智能技术研发、转化和产业服务平台 | E11: 科研转化与项目孵化阶段 | F11: 江苏省产业技术研究院等战略投资 | G11: 中高：省级平台资源强，市场化产品和收入需要进一步拆分 | H11: 江苏省 | I11: 苏州 | J11: 关键器件/平台 | K11: https://www.460.net.cn/news/show-359821.html | L11: 46252
A12: 11 | B12: 景昱医疗科技（苏州）股份有限公司 | C12: 侵入式/DBS脑机接口 | D12: 脑深部电刺激、可感知脑机接口DBS及功能神经疾病治疗系统 | E12: DBS产品已商业化，多项脑机接口产品推进创新审批与临床转化 | F12: D+轮融资3亿元；高瓴、红杉、软银等参与多轮融资 | G12: 高：具备芯片—电极—算法—电池全链能力和临床注册基础 | H12: 江苏省 | I12: 苏州 | J12: 邻近应用/植入调控 | K12: https://www.sceneray.com/ | L12: 46252
A13: 12 | B13: 科斗（苏州）脑机科技有限公司 | C13: 侵入式/神经电生理工具 | D13: 神经微电极、在体电生理设备及脑机接口科研工具 | E13: 40余种产品已商业化，累计服务上千家单位 | F13: 融资情况未充分公开 | G13: 中高：微电极科研工具品类和客户基础较强，是脑机研发上游的卖铲型企业 | H13: 江苏省 | I13: 苏州 | J13: 关键器件/科研平台 | K13: https://www.kedoubc.com/cn/ | L13: 46252
... A33: 32 | B33: 中科意象（南京）科技有限公司 | C33: 侵入式 | D33: 多脑区微创植入式脑机接口与电极植入机器人 | E33: 临床前/系统研发阶段 | F33: 2026年数千万元天使轮 | G33: 中高：中科院自动化所成果转化，机器人+多脑区路线有差异化 | H33: 江苏省 | I33: 南京 | J33: 核心企业 | K33: https://www.460.net.cn/news/show-359821.html | L33: 46252

Sheet 浙江省
A1: 序号 | B1: 公司名称 | C1: 技术路径 | D1: 产品介绍 | E1: 产品临床阶段 | F1: 融资情况 | G1: 竞争力判断 | H1: 所属省份 | I1: 总部城市 | J1: 相关度/类型 | K1: 公开来源 | L1: 核验日期
A2: 1 | B2: 安杰莱科技（杭州）有限公司 | C2: 非侵入式/康复机器人 | D2: 脑机接口系统与肩肘腕手、髋膝踝等系列神经康复机器人 | E2: 产品化和医院应用阶段 | F2: 已获早期融资，金额未充分披露 | G2: 中高：神经康复机器人产品矩阵完整，脑机闭环相关注册与收入需拆分 | H2: 浙江省 | I2: 杭州 | J2: 邻近应用/康复设备 | K2: https://www.sohu.com/a/1017268693_121277055 | L2: 46252
A3: 2 | B3: 博灵医疗（杭州）科技有限公司 | C3: 非侵入式/半侵入式 | D3: 脑卒中康复与脑机接口医疗产品 | E3: 产品研发及医疗注册推进 | F3: 创新医疗战略投资并控股 | G3: 中高：浙大团队与医院资源协同，需观察独立商业化能力 | H3: 浙江省 | I3: 杭州 | J3: 核心企业 | K3: https://www.460.net.cn/news/show-359821.html | L3: 46252
A4: 3 | B4: 创新医疗管理股份有限公司 | C4: 非侵入式/控股布局 | D4: 控股博灵医疗，布局家用穿戴式脑机接口上肢外骨骼和脑机康复系统 | E4: 博灵相关产品已上市销售/推进注册 | F4: A股上市公司，持有博灵医疗约68%股权并持续增资 | G4: 中：通过控股标的快速切入，集团本体研发能力与并表收入需分别评估 | H4: 浙江省 | I4: 诸暨 | J4: 关联布局 | K4: https://pdf.dfcfw.com/pdf/H3_AP202601061816142041_1.pdf?1767725152000.pdf= | L4: 46252
A5: 4 | B5: 杭州程天科技发展有限公司 | C5: 非侵入式/外骨骼康复 | D5: 脑机接口下肢外骨骼康复系统和智能助行机器人 | E5: 外骨骼产品已进入康复场景；脑机接口版本入选国家创新任务 | F5: 已完成多轮融资，具体最新金额未充分公开 | G5: 中高：外骨骼产品化和渠道能力强，脑电意图识别闭环需临床验证 | H5: 浙江省 | I5: 杭州 | J5: 邻近应用/康复设备 | K5: https://kcycrawlerfile.oss-cn-beijing.aliyuncs.com/2026/01/12/900eeb7687194399bf85a452ae3d180c.pdf | L5: 46252
A6: 5 | B6: 杭州辉动科技有限公司 | C6: 非侵入式/康复 | D6: 无创脑机接口智能脑卒中康复系统 | E6: 场景验证/注册推进阶段 | F6: 2025年获战略投资，金额未披露 | G6: 中：康复适应证清晰，临床证据与注册节奏待验证 | H6: 浙江省 | I6: 杭州 | J6: 核心企业 | K6: https://www.460.net.cn/news/show-359821.html | L6: 46252
A7: 6 | B7: 杭州回车电子科技有限公司 | C7: 非侵入式 | D7: 脑电采集硬件、脑控交互与教育/科研产品 | E7: 产品化与教育科研应用阶段 | F7: 已获早期融资，金额未完整披露 | G7: 中：产品落地较早，医疗级应用壁垒仍需建立 | H7: 浙江省 | I7: 杭州 | J7: 核心企业 | K7: https://wap.miit.gov.cn/cms_files/filemanager/1226211233/attach/20256/65ade62451fe4eb09e40e5576208b989.docx | L7: 46252
A8: 7 | B8: 杭州佳量医疗科技有限公司 | C8: 侵入式/神经调控 | D8: 脑机接口、神经刺激与神经调控高端医疗器械 | E8: 多款产品处于注册与临床转化阶段 | F8: 2026年获战略投资；启明、中金、元璟等参与多轮融资 | G8: 高：医工团队、注册经验和神经调控产品线较强 | H8: 浙江省 | I8: 杭州 | J8: 核心企业 | K8: https://www.460.net.cn/news/show-359821.html | L8: 46252
A9: 8 | B9: 杭州科无涯生命科技有限公司 | C9: 侵入式/科研电生理 | D9: 在体多通道电生理、侵入式电极、刺激与数据分析平台 | E9: 科研工具产品化，2025年签约落地余杭 | F9: 融资情况未公开 | G9: 中：电极—采集—分析生态适合脑机研发，临床产品和客户规模尚待核验 | H9: 浙江省 | I9: 杭州 | J9: 关键器件/科研平台 | K9: https://www.sohu.com/a/1017268693_121277055 https://finance.sina.com.cn/jjxw/2025-12-11/doc-inhamhsi8155176.shtml | L9: 46252
A10: 9 | B10: 杭州米福科技有限公司 | C10: 非侵入式/磁电刺激 | D10: 经颅磁电刺激系统及耳迷走神经刺激等神经调控产品 | E10: 入选2025年人工智能医疗器械创新任务，处于研发/注册推进阶段 | F10: 融资情况未充分公开 | G10: 中：神经调控产品线与脑机治疗端相关，闭环感知能力和临床数据需补充 | H10: 浙江省 | I10: 杭州 | J10: 邻近应用/神经调控 | K10: https://kcycrawlerfile.oss-cn-beijing.aliyuncs.com/2026/01/12/900eeb7687194399bf85a452ae3d180c.pdf | L10: 46252
A11: 10 | B11: 杭州暖芯迦电子科技有限公司 | C11: 侵入式/视觉脑机与传感 | D11: 神经接口、生物传感、视觉重建及医疗级生理参数采集模组 | E11: 关键器件产品化；视觉脑机处于动物验证/临床探索阶段 | F11: 融资情况未充分公开 | G11: 中高：既有传感器量产基础并参与标准制定，视觉重建临床周期较长 | H11: 浙江省 | I11: 杭州 | J11: 关键器件/平台 | K11: https://finance.sina.com.cn/wm/2026-03-10/doc-inhqpnue6083089.shtml | L11: 46252
A12: 11 | B12: 杭州诺为医疗技术有限公司 | C12: 侵入式/闭环癫痫调控 | D12: 面向难治性癫痫的闭环神经调控系统 | E12: 入选2025年人工智能医疗器械创新任务，处于研发/注册阶段 | F12: 已被佳量医疗整合，独立融资情况未充分公开 | G12: 中高：闭环癫痫适应证和团队协同明确，需关注整合后的主体、临床与注册进度 | H12: 浙江省 | I12: 杭州 | J12: 邻近应用/植入调控 | K12: https://cn.genlight.com/aboutus https://kcycrawlerfile.oss-cn-beijing.aliyuncs.com/2026/01/12/900eeb7687194399bf85a452ae3d180c.pdf | L12: 46252
A13: 12 | B13: 杭州青石永隽医疗设备有限公司 | C13: 侵入式/闭环神经调控 | D13: 面向难治性抑郁症的AI闭环植入式神经调控系统 | E13: 一代产品完成开发，动物验证与科研型临床推进，进入型检阶段 | F13: 2025年博肽智投等战略入股；后续A轮信息未完整披露 | G13: 中高：适应证和闭环路线清晰，注册与长期疗效是核心里程碑 | H13: 浙江省 | I13: 杭州 | J13: 核心企业 | K13: https://www.biotests.com.cn/newsDetail.aspx?id=86 | L13: 46252
... A28: 27 | B28: 浙江微脑科技有限公司 | C28: 非侵入式 | D28: 脑电感知控制、脑控型智能硬件和可穿戴设备 | E28: 产品化/场景验证阶段 | F28: 2020年获股权投资，金额未披露 | G28: 中：脑控硬件定位明确，商业规模与技术指标披露有限 | H28: 浙江省 | I28: 诸暨 | J28: 核心企业 | K28: https://www.460.net.cn/news/show-359821.html | L28: 46252

Sheet 安徽省
A1: 序号 | B1: 公司名称 | C1: 技术路径 | D1: 产品介绍 | E1: 产品临床阶段 | F1: 融资情况 | G1: 竞争力判断 | H1: 所属省份 | I1: 总部城市 | J1: 相关度/类型 | K1: 公开来源 | L1: 核验日期
A2: 1 | B2: 安徽科大讯飞医疗信息技术有限公司 | C2: 非侵入式/AI解码 | D2: 语音、认知与医疗AI结合的脑机交互研究与智能助听产品 | E2: 项目研发与示范应用阶段 | F2: 科大讯飞体系投入，专项融资未披露 | G2: 中：AI能力强，BCI硬件与临床产品相关度相对间接 | H2: 安徽省 | I2: 合肥 | J2: 关联布局 | K2: https://wap.miit.gov.cn/cms_files/filemanager/1226211233/attach/20249/ef5f470ac75a4fd2834a056c4ae7239b.pdf | L2: 46252
A3: 2 | B3: 合肥哈工艾斯德康智能科技有限公司 | C3: 非侵入式 | D3: 孤独症筛查诊断、脑功能评估、BCI平台与数字疗法 | E3: 已获安徽省首张BCI医疗注册证，产品覆盖多省 | F3: 2025年Pre-A轮千万级；获地方天使基金持续投资 | G3: 中高：注册与商业化进度较好，数据泛化和支付路径需观察 | H3: 安徽省 | I3: 合肥 | J3: 核心企业 | K3: https://www.hfasdre.com/about.html | L3: 46252
A4: 3 | B4: 合肥脑波脑机智能科技有限公司 | C4: 非侵入式/消费级 | D4: AI可穿戴脑机接口与行业应用硬件 | E4: 研发/产品化阶段 | F4: 2024年天使轮，金额未披露 | G4: 观察：处于早期，技术指标、场景和融资信息有限 | H4: 安徽省 | I4: 合肥 | J4: 核心企业 | K4: https://www.460.net.cn/news/show-359821.html | L4: 46252

Sheet 福建省
A1: 序号 | B1: 公司名称 | C1: 技术路径 | D1: 产品介绍 | E1: 产品临床阶段 | F1: 融资情况 | G1: 竞争力判断 | H1: 所属省份 | I1: 总部城市 | J1: 相关度/类型 | K1: 公开来源 | L1: 核验日期
A2: 1 | B2: 厦门光莆电子股份有限公司 | C2: 非侵入式光学传感 | D2: 三维多模态传感器及非嵌入式脑机接口感知研究 | E2: 原型/合作研发阶段 | F2: A股上市公司自有资金投入 | G2: 观察：光学器件基础较好，脑机接口业务仍处早期探索 | H2: 福建省 | I2: 厦门 | J2: 关联布局 | K2: https://pdf.dfcfw.com/pdf/H301_AP202605101822122234_1.pdf | L2: 46252
A3: 2 | B3: 厦门盈趣科技股份有限公司 | C3: 非侵入式/消费级 | D3: 脑电帽、群体脑科学采集设备、消费级脑机接口与智慧健康产品 | E3: 产品已量产并服务科研/消费场景，医学版本持续拓展 | F3: A股上市公司持续投入并参股合作方 | G3: 中高：硬件量产和海外客户基础突出，医疗级闭环仍在发展 | H3: 福建省 | I3: 厦门 | J3: 核心企业 | K3: https://fdi.swt.fujian.gov.cn/show-28108.html | L3: 46252

Sheet 江西省
A1: 序号 | B1: 公司名称 | C1: 技术路径 | D1: 产品介绍 | E1: 产品临床阶段 | F1: 融资情况 | G1: 竞争力判断 | H1: 所属省份 | I1: 总部城市 | J1: 相关度/类型 | K1: 公开来源 | L1: 核验日期
A2: 1 | B2: 江西脑调控技术发展有限公司 | C2: 非侵入式/磁电刺激 | D2: 经颅磁刺激、脑电大数据分析及非侵入式脑机接口脑电生物反馈治疗仪 | E2: 既有经颅磁产品已商业化，新脑机产品推进研发生产 | F2: 融资情况未公开 | G2: 中高：已有注册产品和采购记录，新增脑机项目具备转化基础 | H2: 江西省 | I2: 南昌 | J2: 邻近应用/神经调控 | K2: https://www.nc.gov.cn/ncszf/xqdt/202603/3368c0c4279a42d59770cb3d0b6e353a.shtml | L2: 46252
A3: 2 | B3: 江西省精一医疗科技有限公司 | C3: 非侵入式/采集与深部刺激 | D3: 8通道脑电采集系统、时间干涉无创脑深部电刺激系统 | E3: 2026年项目落地，处于建设/研发与转化阶段 | F3: 融资情况未公开 | G3: 中高：采集与深部刺激结合度高，企业和产品均处早期 | H3: 江西省 | I3: 南昌 | J3: 邻近应用/早期企业 | K3: https://www.nc.gov.cn/ncszf/xqdt/202603/3368c0c4279a42d59770cb3d0b6e353a.shtml | L3: 46252
A4: 3 | B4: 江西思维智光医疗科技有限公司 | C4: 非侵入式/光磁与脑磁 | D4: 多模态光磁神经调控系统、高精度脑磁图及脑功能精准检测设备 | E4: 2026年项目落地，处于研发与产业化建设阶段 | F4: 融资情况未公开 | G4: 中高：脑磁与光磁调控方向稀缺，工程化、注册和客户验证尚早 | H4: 江西省 | I4: 南昌 | J4: 邻近应用/早期企业 | K4: https://www.nc.gov.cn/ncszf/xqdt/202603/3368c0c4279a42d59770cb3d0b6e353a.shtml | L4: 46252

Sheet 山东省
A1: 序号 | B1: 公司名称 | C1: 技术路径 | D1: 产品介绍 | E1: 产品临床阶段 | F1: 融资情况 | G1: 竞争力判断 | H1: 所属省份 | I1: 总部城市 | J1: 相关度/类型 | K1: 公开来源 | L1: 核验日期
A2: 1 | B2: 济南心语智能电子科技有限公司 | C2: 非侵入式/神经反馈 | D2: VR-EEG-HRV神经反馈、认知训练、多模态身心评估及可穿戴脑电采集器 | E2: 多款产品已上市并在20余个省市应用 | F2: 融资情况未充分公开 | G2: 中高：产品矩阵和区域应用较广，医疗注册与持续收入规模需核验 | H2: 山东省 | I2: 济南 | J2: 邻近应用/脑电系统 | K2: https://www.sohu.com/a/1017268693_121277055 | L2: 46252
A3: 2 | B3: 山东海天智能工程有限公司 | C3: 非侵入式/康复机器人 | D3: 脑机接口康复训练系统、脑控上下肢康复机器人 | E3: 产品已获医疗器械注册并产业化应用 | F3: 经营性发展；专项融资未充分公开 | G3: 高：国内早期获证脑控康复机器人，产品与临床积累较深 | H3: 山东省 | I3: 泰安 | J3: 核心企业 | K3: https://kjt.shandong.gov.cn/art/2022/7/26/art_13364_10298502.html | L3: 46252
A4: 3 | B4: 山东新华医疗器械股份有限公司 | C4: 非侵入式 | D4: 脑机接口康复/监测样机及医疗设备协同 | E4: 样机研发与试制阶段 | F4: A股上市公司自有资金投入 | G4: 中：制造、渠道与注册能力强，但BCI产品仍处预研 | H4: 山东省 | I4: 淄博 | J4: 关联布局 | K4: https://pdf.dfcfw.com/pdf/H301_AP202605101822122234_1.pdf | L4: 46252
A5: 4 | B5: 山东亚华电子股份有限公司 | C5: 非侵入式/病房交互 | D5: 病房智能通讯系统与BCI初步融合 | E5: 概念验证/系统集成阶段 | F5: 上市公司自有资金投入 | G5: 观察：应用场景存在，但核心BCI技术与产品成熟度较低 | H5: 山东省 | I5: 淄博 | J5: 关联布局 | K5: https://pdf.dfcfw.com/pdf/H301_AP202605101822122234_1.pdf | L5: 46252

Sheet 河南省
A1: 序号 | B1: 公司名称 | C1: 技术路径 | D1: 产品介绍 | E1: 产品临床阶段 | F1: 融资情况 | G1: 竞争力判断 | H1: 所属省份 | I1: 总部城市 | J1: 相关度/类型 | K1: 公开来源 | L1: 核验日期
A2: 1 | B2: 汉威科技集团股份有限公司 | C2: 柔性传感/电极 | D2: 柔性脑电传感器、电极与人机交互感知组件 | E2: 器件研发和量产导入阶段 | F2: A股上市公司自有资金投入 | G2: 中高：柔性传感制造能力强，BCI专用产品与客户验证需披露 | H2: 河南省 | I2: 郑州 | J2: 关键器件/平台 | K2: https://www.niiea.org.cn/upload/202601/06/202601061029129486.pdf | L2: 46252
A3: 2 | B3: 河南翔宇医疗设备股份有限公司 | C3: 非侵入式/康复机器人 | D3: 脑机接口神经康复整体解决方案、脑控康复机器人和脑电采集设备 | E3: 多款产品已获证/在医院应用，后续产品持续注册 | F3: 科创板上市公司持续研发投入 | G3: 高：康复渠道、制造和注册能力领先，核心算法差异化需持续验证 | H3: 河南省 | I3: 安阳 | J3: 核心企业 | K3: https://www.xyyl.com/ https://pdf.dfcfw.com/pdf/H2_AN202604231821513670_1.pdf | L3: 46252

Sheet 湖北省
A1: 序号 | B1: 公司名称 | C1: 技术路径 | D1: 产品介绍 | E1: 产品临床阶段 | F1: 融资情况 | G1: 竞争力判断 | H1: 所属省份 | I1: 总部城市 | J1: 相关度/类型 | K1: 公开来源 | L1: 核验日期
A2: 1 | B2: 武汉百英诺生物科技有限公司 | C2: 非侵入式/聚焦超声 | D2: 低频聚焦超声智能无创脑机治疗系统 | E2: 原型/临床转化阶段 | F2: 融资情况未充分公开 | G2: 中高：同济医院孵化、无创调控路线明确；注册与多中心临床仍需推进 | H2: 湖北省 | I2: 武汉 | J2: 邻近应用/神经调控 | K2: https://news.cjn.cn/whpd/yw_19947/202512/t5247825.htm | L2: 46252
A3: 2 | B3: 武汉格林泰克科技有限公司 | C3: 非侵入式电极 | D3: 干/湿头皮电极、降噪与脑电采集组件 | E3: 上游器件研发与供货阶段 | F3: 融资情况未公开 | G3: 中高：上游电极工艺和本地产业链协同价值较高 | H3: 湖北省 | I3: 武汉 | J3: 关键器件/平台 | K3: https://zscqj.hubei.gov.cn/bmdt/ztzl/2023zt/zhlh2023/202601/t20260116_5857083.shtml | L3: 46252
A4: 3 | B4: 武汉沃亿生物科技有限公司 | C4: 脑机接口设备/生物电 | D4: 脑机接口与生物电设备研发制造（公开细节有限） | E4: 研发/产品化阶段 | F4: 融资情况未公开 | G4: 观察：被地方政府列为设备制造企业，需补充产品与注册信息 | H4: 湖北省 | I4: 武汉 | J4: 核心企业 | K4: https://www.yiruide.com/news/404.html | L4: 46252
A5: 4 | B5: 武汉依瑞德医疗设备新技术有限公司 | C5: 非侵入式/神经调控 | D5: TMS、fNIRS、声光电磁多物理因子脑机与神经调控产品 | E5: 多类医疗器械已获证并服务数千家医疗机构 | F5: 经营性发展与产业融资并行，具体轮次未充分公开 | G5: 高：获证矩阵、医院覆盖和制造能力领先，属于无创临床转化头部 | H5: 湖北省 | I5: 武汉 | J5: 核心企业 | K5: https://www.wuhan.gov.cn/sy/whyw/202606/t20260622_2779529.shtml | L5: 46252
A6: 5 | B6: 武汉智普天创科技有限公司 | C6: 非侵入式 | D6: 便携脑电帽、无线脑电采集、认知评估与信号处理系统 | E6: 专利/样机与场景验证阶段 | F6: 融资情况未公开 | G6: 中：专利布局较活跃，产品注册和商业化信息有限 | H6: 湖北省 | I6: 武汉 | J6: 核心企业 | K6: https://zscqj.hubei.gov.cn/bmdt/ztzl/2023zt/zhlh2023/202601/t20260116_5857083.shtml | L6: 46252
A7: 6 | B7: 武汉衷华脑机融合科技发展有限公司 | C7: 侵入式/双向 | D7: HIM60000高通量植入式系统、柔性电极、芯片、解码算法与刺激平台 | E7: 已完成4例短期临床，多条三类器械推进注册 | F7: 产业资本支持；具体轮次金额未完整公开 | G7: 高：通道数、双向刺激和国产全栈能力突出，注册兑现是核心观察点 | H7: 湖北省 | I7: 武汉 | J7: 核心企业 | K7: https://jxt.hubei.gov.cn/bmdt/rdjj/202505/t20250501_5638507.shtml | L7: 46252

Sheet 湖南省
A1: 序号 | B1: 公司名称 | C1: 技术路径 | D1: 产品介绍 | E1: 产品临床阶段 | F1: 融资情况 | G1: 竞争力判断 | H1: 所属省份 | I1: 总部城市 | J1: 相关度/类型 | K1: 公开来源 | L1: 核验日期
A2: 1 | B2: 可孚医疗科技股份有限公司 | C2: 侵入式/非侵入式投资布局 | D2: 投资脑机接口与神经刺激标的，协同家用康复辅具渠道 | E2: 被投产品处于研发/注册阶段 | F2: 战略投资常州瑞神安、苏州纽铃智等，金额未完整披露 | G2: 中：渠道与资本协同价值高，但自身核心BCI研发相关度较低 | H2: 湖南省 | I2: 长沙 | J2: 关联布局 | K2: https://pdf.dfcfw.com/pdf/H301_AP202605101822122234_1.pdf | L2: 46252

Sheet 广东省
A1: 序号 | B1: 公司名称 | C1: 技术路径 | D1: 产品介绍 | E1: 产品临床阶段 | F1: 融资情况 | G1: 竞争力判断 | H1: 所属省份 | I1: 总部城市 | J1: 相关度/类型 | K1: 公开来源 | L1: 核验日期
A2: 1 | B2: 东莞市冠隆医疗科技有限公司 | C2: 非侵入式/脑电电极 | D2: 脑电电极、脑电帽、脑电采集系统及OEM/ODM服务 | E2: 产品已服务科研与临床客户，具备规模化定制能力 | F2: 融资情况未公开 | G2: 中高：脑电电极品类和制造基础明确，是非侵入式脑机的重要上游 | H2: 广东省 | I2: 东莞 | J2: 关键器件/供应链 | K2: https://www.kwanlon.com/ | L2: 46252
A3: 2 | B3: 广州华南脑控智能科技有限公司 | C3: 非侵入式 | D3: 脑控轮椅、智慧病房、脑机AI交互与康复方案 | E3: 产品化/场景应用阶段 | F3: 完成多轮融资，公开金额不完整 | G3: 中高：华南理工技术基础和场景落地较早，医疗注册与规模收入待核验 | H3: 广东省 | I3: 广州 | J3: 核心企业 | K3: https://pdf.dfcfw.com/pdf/H301_AP202605101822122234_1.pdf | L3: 46252
A4: 3 | B4: 广州迈普再生医学科技股份有限公司 | C4: 侵入式/神经外科耗材 | D4: 人工硬脑（脊）膜等神经外科植入材料，为海外脑机临床项目提供相关产品 | E4: 神经外科产品已商业化；脑机接口属于供应链关联 | F4: 科创板上市公司自有资金投入 | G4: 中：注册和神经外科材料能力成熟，但脑机接口专用收入相关度较低 | H4: 广东省 | I4: 广州 | J4: 关键器件/供应链 | K4: https://pdf.dfcfw.com/pdf/H3_AP202601061816142041_1.pdf?1767725152000.pdf= | L4: 46252
A5: 4 | B5: 广州析芒医疗科技有限公司 | C5: 侵入式 | D5: 快速临床转化的植入式脑机接口系统 | E5: 已开展多物种动物试验与临床前研究 | F5: 2025年获广州国资与产业基金战略投资，金额未披露 | G5: 中高：临床导向明确，处于临床前关键验证期 | H5: 广东省 | I5: 广州 | J5: 核心企业 | K5: https://www.460.net.cn/news/show-359821.html | L5: 46252
A6: 5 | B6: 佳禾智能科技股份有限公司 | C6: 非侵入式 | D6: 12通道脑电传感头戴设备与脑电通信系统 | E6: 样机/客户验证阶段 | F6: 上市公司自有资金投入 | G6: 中：消费电子量产能力强，脑电信号质量与应用闭环是关键 | H6: 广东省 | I6: 东莞 | J6: 关联布局 | K6: https://pdf.dfcfw.com/pdf/H301_AP202605101822122234_1.pdf | L6: 46252
A7: 6 | B7: 诺尔医疗（深圳）有限公司 | C7: 侵入式/精准脑电 | D7: MRI兼容SEEG颅内电极、癫痫AI辅助诊断和射频/激光消融产品 | E7: SEEG颅内深部电极已获NMPA三类证，后续产品持续研发 | F7: 已完成A轮等多轮融资，累计金额未完整披露 | G7: 高：侵入式脑电、算法和临床场景结合紧密，具备从定位到治疗的闭环潜力 | H7: 广东省 | I7: 深圳 | J7: 邻近应用/侵入电生理 | K7: https://www.neurox.cn/ | L7: 46252
A8: 7 | B8: 熵基科技股份有限公司 | C8: 非侵入式 | D8: 脑电穿戴原型、教育/医疗/养老多模态交互 | E8: 原型/场景验证阶段 | F8: 上市公司自有资金投入 | G8: 中：硬件制造与渠道优势明显，BCI核心算法和医疗价值待验证 | H8: 广东省 | I8: 东莞 | J8: 关联布局 | K8: https://pdf.dfcfw.com/pdf/H301_AP202605101822122234_1.pdf | L8: 46252
A9: 8 | B9: 深圳德力凯医疗电子股份有限公司 | C9: 非侵入式/临床脑电监测 | D9: 经颅多普勒、脑电图机及颅脑疾病诊疗产品 | E9: 脑电图产品覆盖900余家医院，拥有多项医疗器械注册 | F9: 融资情况未充分公开 | G9: 中高：临床脑电设备和渠道基础扎实，可作为脑机接口数据采集入口 | H9: 广东省 | I9: 深圳 | J9: 邻近应用/临床电生理 | K9: https://www.sohu.com/a/1017268693_121277055 | L9: 46252
A10: 9 | B10: 深圳瀚翔脑科学技术股份有限公司 | C10: 非侵入式/TMS-EEG | D10: 脑科学科研工具、TMS-EEG和精神神经疾病精准诊疗整体方案 | E10: 科研与临床产品已商业化，具体注册清单需逐项核验 | F10: 融资情况未充分公开 | G10: 中高：TMS-EEG闭环技术和科研客户基础较强，规模化医疗收入待披露 | H10: 广东省 | I10: 深圳 | J10: 邻近应用/脑科学平台 | K10: https://www.sohu.com/a/1017268693_121277055 | L10: 46252
A11: 10 | B11: 深圳欢影医疗科技有限公司 | C11: 非侵入式/神经调控 | D11: 非植入式神经调控与脑机接口相关医疗器械研发 | E11: 研发/临床转化阶段，公开产品细节有限 | F11: 融资情况未公开 | G11: 观察：已进入专业产业数据库，但产品、资质和团队信息仍需进一步核验 | H11: 广东省 | I11: 深圳 | J11: 邻近应用/早期企业 | K11: https://data.yiyun.co/s?son_channel_id=456 | L11: 46252
A12: 11 | B12: 深圳鹏脑科技有限公司 | C12: 非侵入式 | D12: 面向认知障碍、多动症和睡眠障碍的脑机接口+AI产品 | E12: 研发/临床合作阶段 | F12: 2025年数千万元天使轮，同创伟业投资 | G12: 中：场景丰富但早期，需要优先聚焦适应证与证据 | H12: 广东省 | I12: 深圳 | J12: 核心企业 | K12: https://www.460.net.cn/news/show-359821.html | L12: 46252
A13: 12 | B13: 深圳锐盟半导体有限公司 | C13: 脑机接口芯片 | D13: AI与人机交互处理器芯片，覆盖材料—器件—芯片—算法 | E13: 芯片研发与客户验证阶段 | F13: 2026年近亿元A轮，松禾资本领投 | G13: 中高：上游芯片稀缺，需验证BCI专用性能和量产客户 | H13: 广东省 | I13: 深圳 | J13: 关键器件/平台 | K13: https://www.460.net.cn/news/show-359821.html | L13: 46252
... A21: 20 | B21: 深圳中科华意科技有限公司 | C21: 非侵入式闭环调控 | D21: BCI-tES闭环解决方案、便携式经颅电刺激训练仪 | E21: 产品化与临床合作阶段 | F21: 2024年数千万元Pre-A+轮 | G21: 中高：中科院孵化、闭环系统完整，商业化仍在扩展 | H21: 广东省 | I21: 深圳 | J21: 核心企业 | K21: https://www.460.net.cn/news/show-359821.html | L21: 46252

Sheet 海南省
A1: 序号 | B1: 公司名称 | C1: 技术路径 | D1: 产品介绍 | E1: 产品临床阶段 | F1: 融资情况 | G1: 竞争力判断 | H1: 所属省份 | I1: 总部城市 | J1: 相关度/类型 | K1: 公开来源 | L1: 核验日期
A2: 1 | B2: 神芯科技（海南）有限公司 | C2: 侵入式芯片 | D2: 脑机接口核心芯片、神经信号采集/刺激与闭环器件 | E2: 研发/客户验证阶段 | F2: 2025年千万级天使轮；2026年再获数千万元融资 | G2: 中高：海南大学团队与专用芯片方向稀缺，量产与客户验证是关键 | H2: 海南省 | I2: 海口 | J2: 关键器件/平台 | K2: https://www.sensingx.com/ https://www.460.net.cn/news/show-359821.html | L2: 46252

Sheet 重庆市
A1: 序号 | B1: 公司名称 | C1: 技术路径 | D1: 产品介绍 | E1: 产品临床阶段 | F1: 融资情况 | G1: 竞争力判断 | H1: 所属省份 | I1: 总部城市 | J1: 相关度/类型 | K1: 公开来源 | L1: 核验日期
A2: 1 | B2: 重庆脑际医疗科技有限公司 | C2: 非侵入式/侵入式布局 | D2: 高导联脑电、柔性电极、癫痫植入调控与无创神经调控设备 | E2: 脑电产品商业化；植入式方向处于临床转化阶段 | F2: 融资情况未充分公开 | G2: 中高：覆盖采集—分析—调控全链条，需核验植入产品注册节点 | H2: 重庆市 | I2: 重庆 | J2: 核心企业 | K2: https://www.brainspace.com.cn/ | L2: 46252
A3: 2 | B3: 重庆云脑医疗科技有限公司 | C3: 非侵入式/康复 | D3: 脑电诱发康复训练、手功能与下肢外骨骼脑机系统 | E3: 脑机接口康复训练系统已获二类医疗器械注册证并规模化应用 | F3: 融资情况未充分公开 | G3: 高：注册证、医院应用与患者规模形成先发优势 | H3: 重庆市 | I3: 重庆 | J3: 核心企业 | K3: https://jkq.cq.gov.cn/zwxx/jkdt/202508/t20250825_14933166_wap.html https://yunnaomedical.com/ | L3: 46252

Sheet 四川省
A1: 序号 | B1: 公司名称 | C1: 技术路径 | D1: 产品介绍 | E1: 产品临床阶段 | F1: 融资情况 | G1: 竞争力判断 | H1: 所属省份 | I1: 总部城市 | J1: 相关度/类型 | K1: 公开来源 | L1: 核验日期
A2: 1 | B2: 成都市前沿类脑人工智能创新中心有限公司 | C2: 非侵入式/成果转化平台 | D2: 脑功能评估、孤独症辅助诊断与脑机接口成果转化平台 | E2: 产品研发与场景应用阶段 | F2: 融资情况未充分公开 | G2: 中高：电子科大科研资源和项目承接能力突出，市场化产品需单独核验 | H2: 四川省 | I2: 成都 | J2: 产业平台 | K2: https://www.kczg.org.cn/org/orgdetail?id=349461 | L2: 46252
A3: 2 | B3: 成都瓦博科技有限公司 | C3: 非侵入式/消费级 | D3: 消费级脑机接口硬件，强调算法压缩与低成本算力路线 | E3: 研发/产品定义阶段 | F3: 2026年种子轮，策源资本投资，金额未披露 | G3: 观察：团队与融资较新，产品、量产和用户验证尚早 | H3: 四川省 | I3: 成都 | J3: 核心企业 | K3: https://www.460.net.cn/news/show-359821.html | L3: 46252
A4: 3 | B4: 成都芯脑科技有限公司 | C4: 非侵入式 | D4: 孤独症脑网络标志物、筛查评估与脑机辅助干预平台 | E4: 产品已服务多地患者并开展场景应用，注册信息需持续核验 | F4: 产业化运营中，具体融资未充分公开 | G4: 中高：数据与真实场景积累突出，疗效口径需以注册临床证据复核 | H4: 四川省 | I4: 成都 | J4: 核心企业 | K4: https://district.ce.cn/newarea/roll/202607/t20260721_3098650.shtml | L4: 46252
A5: 4 | B5: 格式塔（成都）科技有限公司（Gestala） | C5: 超声脑机接口 | D5: 全脑超声读写平台，首款产品聚焦慢性疼痛管理 | E5: 临床前/产品研发；计划启动国家药监局注册流程 | F5: 2026年完成1.5亿元天使轮及4.2亿元天使+轮，半年累计5.7亿元 | G5: 高：超声路线稀缺、资本和团队突出；技术验证与安全性仍是高风险节点 | H5: 四川省 | I5: 成都 | J5: 核心企业 | K5: https://sichuan.scol.com.cn/ggxw/202606/83277803.html | L5: 46252
A6: 5 | B6: 四川必可明科技有限公司 | C6: 非侵入式光学脑机接口 | D6: 便携式脑功能定量成像、认知评估与训练软件 | E6: 产品展示与场景验证阶段 | F6: 融资情况未公开 | G6: 中：光学路线差异化明显，医疗注册与临床证据待补充 | H6: 四川省 | I6: 成都 | J6: 核心企业 | K6: https://bcomingtech.com/ | L6: 46252
A7: 6 | B7: 四川君健万峰医疗器械有限责任公司 | C7: 神经调控/脑机接口 | D7: 高端神经调控与脑机接口医疗设备 | E7: 研发/注册筹备阶段 | F7: 融资情况未充分公开 | G7: 观察：产业协同意愿明确，需核验具体产品和注册节点 | H7: 四川省 | I7: 成都 | J7: 核心企业 | K7: https://www.jjwf-med.com/nd.jsp?id=18 | L7: 46252
A8: 7 | B8: 四川脑佳科技有限公司 | C8: AI脑机接口 | D8: AI脑信号解析与脑机接口应用产品 | E8: 研发/成果转化阶段 | F8: 融资情况未公开 | G8: 观察：院士成果转化背景，公开产品与商业数据有限 | H8: 四川省 | I8: 成都 | J8: 核心企业 | K8: https://www.nbd.com.cn/articles/2026-04-28/4367652.html | L8: 46252
A9: 8 | B9: 四川省博瑞恩科技有限公司 | C9: 非侵入式/科研平台 | D9: 脑机接口、脑器交互、群脑超扫描和睡眠调控科研设备 | E9: 科研设备与技术服务已商业化 | F9: 融资情况未充分公开 | G9: 中：本地科研服务和集成能力突出，医疗级壁垒相对有限 | H9: 四川省 | I9: 成都 | J9: 关键器件/平台 | K9: https://www.boruienbrain.com/ | L9: 46252
A10: 9 | B10: 四川新源生物电子科技有限公司 | C10: 非侵入式/脑电监测 | D10: 脑电/生物信号采集、脑科学研究设备与临床辅助诊断工具 | E10: 科研产品商业化；医疗产品持续注册和临床合作 | F10: 2020年3000万元天使轮；2024年数千万元Pre-A轮 | G10: 中高：产品与融资基础较扎实，华西临床合作有利于转化 | H10: 四川省 | I10: 成都 | J10: 核心企业 | K10: https://www.neurogin.com/about-us.html | L10: 46252
A11: 10 | B11: 中科睿控（成都）科技有限公司 | C11: 非侵入式/消费级 | D11: 可穿戴脑机接口设备与智能硬件 | E11: 产品化/场景验证阶段 | F11: 2026年获超千万元战略投资 | G11: 中：中科院成果转化，落地速度快；核心技术和收入规模待核验 | H11: 四川省 | I11: 成都 | J11: 核心企业 | K11: https://www.460.net.cn/news/show-359821.html | L11: 46252
A12: 11 | B12: 中科院成都信息技术股份有限公司（中科信息） | C12: 非侵入式/闭环系统 | D12: 基于光遗传调控的闭环脑机接口、智慧麻醉和智慧康复 | E12: 科研项目与样机研发阶段 | F12: A股上市公司自有资金投入 | G12: 中：AI和系统集成能力强，脑机接口业务尚未形成规模化收入 | H12: 四川省 | I12: 成都 | J12: 关联布局 | K12: https://pdf.dfcfw.com/pdf/H301_AP202605101822122234_1.pdf | L12: 46252

Sheet 贵州省
A1: 序号 | B1: 公司名称 | C1: 技术路径 | D1: 产品介绍 | E1: 产品临床阶段 | F1: 融资情况 | G1: 竞争力判断 | H1: 所属省份 | I1: 总部城市 | J1: 相关度/类型 | K1: 公开来源 | L1: 核验日期
A2: 1 | B2: 贵州数脑科技有限公司 | C2: 非侵入式/康复运营 | D2: 脑机接口康复训练系统、云平台和医院—社区—家庭康复网络 | E2: 2026年成立并承载贵州首个脑机接口产业化项目 | F2: 融资情况未公开 | G2: 观察：区域首发和场景落地价值明确，核心设备来源与自研能力需持续核验 | H2: 贵州省 | I2: 贵阳 | J2: 产业项目/渠道 | K2: https://szb.eyesnews.cn/pc/cont/202607/13/content_184156.html | L2: 46252

Sheet 云南省
A1: 序号 | B1: 公司名称 | C1: 技术路径 | D1: 产品介绍 | E1: 产品临床阶段 | F1: 融资情况 | G1: 竞争力判断 | H1: 所属省份 | I1: 总部城市 | J1: 相关度/类型 | K1: 公开来源 | L1: 核验日期
A2: 1 | B2: 脑次元（昆明）智能科技有限公司 | C2: 非侵入式/脑健康运营 | D2: 脑电AI解码、脑神经节律调控及康养服务 | E2: 2026年成立，处于区域运营和场景导入阶段 | F2: 融资情况未公开 | G2: 观察：依托浙江总部技术进入西南，需区分直营网点能力与独立技术资产 | H2: 云南省 | I2: 昆明 | J2: 产业项目/渠道 | K2: https://www.sohu.com/a/1033080445_122759515 | L2: 46252

Sheet 陕西省
A1: 序号 | B1: 公司名称 | C1: 技术路径 | D1: 产品介绍 | E1: 产品临床阶段 | F1: 融资情况 | G1: 竞争力判断 | H1: 所属省份 | I1: 总部城市 | J1: 相关度/类型 | K1: 公开来源 | L1: 核验日期
A2: 1 | B2: 西安穹顶医疗科技有限公司 | C2: 非侵入式深脑调控 | D2: 治疗型脑机接口与无创深脑调控产品矩阵 | E2: 临床/注册推进阶段 | F2: 2026年完成近亿元A+轮 | G2: 中高：治疗型定位与西交大团队突出，临床数据和获证节奏关键 | H2: 陕西省 | I2: 西安 | J2: 核心企业 | K2: https://www.cnfin.com/sl-lb/detail/20260509/4411387_1.html | L2: 46252
A3: 2 | B3: 西安臻泰智能科技有限公司 | C3: 非侵入式/康复机器人 | D3: 脑机接口智能康复机器人及整体解决方案 | E3: 产品已在多家医院应用，推进三类器械申报 | F3: 天使轮和A轮；联想创投、胡杨林资本、奇绩创坛等参与 | G3: 中高：康复落地较早，需持续核验获证与规模收入 | H3: 陕西省 | I3: 西安 | J3: 核心企业 | K3: https://www.460.net.cn/news/show-359821.html | L3: 46252
